hkcr/__init__.py
hkcr/__main__.py
hkcr/api.py
hkcr/types.py
hkcr-0.1.0.dist-info/METADATA
hkcr-0.1.0.dist-info/WHEEL
hkcr-0.1.0.dist-info/entry_points.txt
hkcr-0.1.0.dist-info/RECORD
