Metadata-Version: 2.4
Name: hkcr
Version: 0.1.0
Summary: Hong Kong Companies Registry Search SDK
Project-URL: Homepage, https://github.com/rocky/hkcompsearch
License-Expression: MIT
Keywords: api,companies,hong kong,registry,search
Classifier: Development Status :: 4 - Beta
Classifier: Intended Audience :: Developers
Classifier: License :: OSI Approved :: MIT License
Classifier: Programming Language :: Python :: 3
Classifier: Programming Language :: Python :: 3.9
Classifier: Programming Language :: Python :: 3.10
Classifier: Programming Language :: Python :: 3.11
Classifier: Programming Language :: Python :: 3.12
Requires-Python: >=3.9
